vinca/__init__.py
vinca/_browser.py
vinca/_card.py
vinca/_cardlist.py
vinca/_cli_objects.py
vinca/_config.py
vinca/_dolt.py
vinca/_lib/__init__.py
vinca/_lib/ansi.py
vinca/_lib/julianday.py
vinca/_lib/readkey.py
vinca/_lib/terminal.py
vinca/_lib/unicode_bitmaps.py
vinca/_lib/video.py
vinca/_scheduling.py
vinca/_statistics.py
vinca/empty_deck.db
vinca/tutorial_cards.db
vinca-2.4.7.dist-info/entry_points.txt
vinca-2.4.7.dist-info/LICENSE
vinca-2.4.7.dist-info/WHEEL
vinca-2.4.7.dist-info/METADATA
vinca-2.4.7.dist-info/RECORD
